setup.py
pycproject/__init__.py
pycproject/convert2amidict.py
pycproject/convert2elasticdump.py
pycproject/factnet.py
pycproject/readctree.py
pycproject.egg-info/PKG-INFO
pycproject.egg-info/SOURCES.txt
pycproject.egg-info/dependency_links.txt
pycproject.egg-info/not-zip-safe
pycproject.egg-info/requires.txt
pycproject.egg-info/top_level.txt